pacoteTestePypi/__init__.py
pacoteTestePypi/modulo.py
pacoteTestePypi-0.0.1.dist-info/LICENSE
pacoteTestePypi-0.0.1.dist-info/METADATA
pacoteTestePypi-0.0.1.dist-info/WHEEL
pacoteTestePypi-0.0.1.dist-info/top_level.txt
pacoteTestePypi-0.0.1.dist-info/RECORD
