Metadata-Version: 2.1
Name: pacoteTestePypi
Version: 0.0.1
Summary: Pacote python para exibir número de 1 a 9
Home-page: UNKNOWN
Author: Renan Rodrigues Moreira
Author-email: renanmoreira_@outlook.com
License: MIT License
Keywords: Pacote
Platform: UNKNOWN
License-File: LICENSE
Requires-Dist: numpy
